swipp/__init__.py
swipp/curve.py
swipp/curveset.py
swipp/curvesuite.py
swipp/curveuncertain.py
swipp/dispersioncurve.py
swipp/dispersionset.py
swipp/dispersionsuite.py
swipp/groundmodel.py
swipp/groundmodelsuite.py
swipp/parameter.py
swipp/parameterization.py
swipp/regex.py
swipp/suite.py
swipp/target.py
swprepost/__init__.py
swprepost/check_utils.py
swprepost/curve.py
swprepost/curveuncertain.py
swprepost/dispersioncurve.py
swprepost/dispersionset.py
swprepost/dispersionsuite.py
swprepost/groundmodel.py
swprepost/groundmodelsuite.py
swprepost/meta.py
swprepost/modaltarget.py
swprepost/parameter.py
swprepost/parameterization.py
swprepost/regex.py
swprepost/suite.py
swprepost/target.py
swprepost/targetset.py
swprepost-2.0.0.dist-info/LICENSE.txt
swprepost-2.0.0.dist-info/METADATA
swprepost-2.0.0.dist-info/WHEEL
swprepost-2.0.0.dist-info/top_level.txt
swprepost-2.0.0.dist-info/RECORD
