Metadata-Version: 2.1
Name: swprepost
Version: 2.0.0
Summary: A Python Package for Surface Wave Inversion Pre- and Post-Processing
Home-page: https://github.com/jpvantassel/swprepost
Author: Joseph P. Vantassel
Author-email: jvantassel@utexas.edu
License: UNKNOWN
Keywords: surface wave inversion geopsy pre-process post-process dispersion surface waves
Platform: UNKNOWN
Classifier: Development Status :: 5 - Production/Stable
Classifier: Intended Audience :: Developers
Classifier: Intended Audience :: Education
Classifier: Intended Audience :: Science/Research
Classifier: Topic :: Education
Classifier: Topic :: Scientific/Engineering
Classifier: Topic :: Scientific/Engineering :: Physics
Classifier: License :: OSI Approved :: GNU General Public License v3 or later (GPLv3+)
Classifier: Programming Language :: Python :: 3.6
Classifier: Programming Language :: Python :: 3.7
Classifier: Programming Language :: Python :: 3.8
Classifier: Programming Language :: Python :: 3.9
Classifier: Programming Language :: Python :: 3.10
Requires-Python: >3.6
Requires-Dist: matplotlib
Requires-Dist: numpy
Requires-Dist: scipy
Provides-Extra: dev
Requires-Dist: coverage ; extra == 'dev'
Requires-Dist: hypothesis ; extra == 'dev'
Requires-Dist: jupyterlab ; extra == 'dev'
Requires-Dist: nbformat ; extra == 'dev'
Requires-Dist: tox ; extra == 'dev'
